Metadata-Version: 2.1
Name: simple-roman-numbers
Version: 0.1.3
Summary: Create a RomanNumber class to be able to do basic calculations with Roman numerals.
Home-page: https://github.com/digestiveThinking/roman_numbers
Author: Mon Maldonado
Author-email: monterdi@gmail.com
Classifier: Programming Language :: Python :: 3
Classifier: License :: OSI Approved :: MIT License
Classifier: Operating System :: OS Independent
Requires-Python: >=3.6
License-File: LICENSE
